cli/__init__.py
cli/utils.py
cli/data/.gitignore
cli/data/Dockerfile
cli/data/config.json
flowmagic_cli-0.1.dist-info/METADATA
flowmagic_cli-0.1.dist-info/WHEEL
flowmagic_cli-0.1.dist-info/entry_points.txt
flowmagic_cli-0.1.dist-info/top_level.txt
flowmagic_cli-0.1.dist-info/RECORD
