Metadata-Version: 2.1
Name: flowmagic-cli
Version: 0.1
Summary: FlowMagic Cli
Home-page: https://flowmagic.io/
Author: Arka Nayan
Author-email: hello@flowmagic.io
License: UNKNOWN
Platform: UNKNOWN
Classifier: Programming Language :: Python
Classifier: Programming Language :: Python :: 3 :: Only
Classifier: Environment :: Console
Classifier: Intended Audience :: Developers
Classifier: Intended Audience :: System Administrators
Classifier: Topic :: Internet :: WWW/HTTP
Classifier: Topic :: Software Development
Classifier: Topic :: System :: Networking
Classifier: Topic :: Terminals
Classifier: Topic :: Text Processing
Classifier: Topic :: Utilities
Requires-Python: >=3.6
Requires-Dist: click (>=7.1.2)
Requires-Dist: requests (>=2.24.0)
